lx_anonymizer/.gitignore
lx_anonymizer/__init__.py
lx_anonymizer/asessment.py
lx_anonymizer/citations.bib
lx_anonymizer/frame_cleaner.py
lx_anonymizer/main_with_reassembly.py
lx_anonymizer/pipeline_manager.py
lx_anonymizer/report_reader.py
lx_anonymizer/schema.py
lx_anonymizer/sensitive_meta_interface.py
lx_anonymizer/anonymization/anonymizer.py
lx_anonymizer/anonymization/blur.py
lx_anonymizer/anonymization/masking.py
lx_anonymizer/anonymization/sensitive_region_cropper.py
lx_anonymizer/anonymization/text_anonymizer.py
lx_anonymizer/anonymization/masks/fujifilm_4450hd_mask.json
lx_anonymizer/anonymization/masks/generic_mask.json
lx_anonymizer/anonymization/masks/olympus_cv_1500_mask.json
lx_anonymizer/anonymization/masks/pentax_ept_7000_mask.json
lx_anonymizer/devices/default.json
lx_anonymizer/devices/olympus_cv_1500.json
lx_anonymizer/generated_reports/keywords_20250414_161025.json
lx_anonymizer/generated_reports/keywords_20250414_161405.json
lx_anonymizer/generated_reports/keywords_20250414_161642.json
lx_anonymizer/generated_reports/keywords_20250414_162856.json
lx_anonymizer/generated_reports/keywords_20250414_163025.json
lx_anonymizer/generated_reports/keywords_20250414_163047.json
lx_anonymizer/generated_reports/keywords_20250414_163103.json
lx_anonymizer/generated_reports/keywords_20250414_163118.json
lx_anonymizer/generated_reports/keywords_20250414_163138.json
lx_anonymizer/generated_reports/keywords_20250414_163150.json
lx_anonymizer/generated_reports/keywords_20250414_163202.json
lx_anonymizer/generated_reports/keywords_20250414_163214.json
lx_anonymizer/generated_reports/keywords_20250414_163238.json
lx_anonymizer/generated_reports/keywords_20250414_163253.json
lx_anonymizer/generated_reports/keywords_20250414_163312.json
lx_anonymizer/generated_reports/keywords_20250414_163323.json
lx_anonymizer/generated_reports/keywords_20250414_163337.json
lx_anonymizer/generated_reports/keywords_20250414_163353.json
lx_anonymizer-0.8.9.11.dist-info/METADATA
lx_anonymizer-0.8.9.11.dist-info/WHEEL
lx_anonymizer-0.8.9.11.dist-info/entry_points.txt
lx_anonymizer-0.8.9.11.dist-info/licenses/LICENSE
lx_anonymizer-0.8.9.11.dist-info/RECORD
