Metadata-Version: 2.4
Name: lx-anonymizer
Version: 0.8.9.11
Summary: OCR-driven anonymization pipeline for medical reports and endoscopy frames
Project-URL: Changelog, https://github.com/wg-lux/lx-anonymizer/blob/main/CHANGELOG.md
Project-URL: Documentation, https://github.com/wg-lux/lx-anonymizer#readme
Project-URL: Homepage, https://github.com/wg-lux/lx-anonymizer
Project-URL: Issue Tracker, https://github.com/wg-lux/lx-anonymizer/issues
Author-email: Max Hild <maxhild10@gmail.com>, "Thomas J. Lux" <lux_t1@ukw.de>
Maintainer-email: WG Lux <lux@coloreg.de>
License: MIT License
License-File: LICENSE
Keywords: anonymization,medical,nlp,ocr,privacy
Classifier: Development Status :: 4 - Beta
Classifier: Intended Audience :: Healthcare Industry
Classifier: License :: OSI Approved :: MIT License
Classifier: Natural Language :: German
Classifier: Operating System :: POSIX :: Linux
Classifier: Programming Language :: Python
Classifier: Programming Language :: Python :: 3
Classifier: Programming Language :: Python :: 3 :: Only
Classifier: Programming Language :: Python :: 3.12
Classifier: Programming Language :: Python :: 3.13
Classifier: Topic :: Scientific/Engineering :: Image Processing
Classifier: Topic :: Scientific/Engineering :: Medical Science Apps.
Classifier: Topic :: Text Processing :: Linguistic
Requires-Python: >=3.12
Requires-Dist: certifi>=2024.8.30
Requires-Dist: dateparser>=1.2.1
Requires-Dist: django>=5.2.7
Requires-Dist: faker>=37.1.0
Requires-Dist: flair>=0.15.1
Requires-Dist: gender-guesser>=0.4.0
Requires-Dist: imutils>=0.5.4
Requires-Dist: numpy>=1.26.0
Requires-Dist: opencv-python>=4.10.0.84
Requires-Dist: opencv-stubs>=0.1.1
Requires-Dist: pandas>=2.3.3
Requires-Dist: pdfplumber>=0.11.7
Requires-Dist: pillow>=10.4.0
Requires-Dist: pip>=25.2
Requires-Dist: pre-commit>=4.5.1
Requires-Dist: protobuf>=6.30.2
Requires-Dist: pydantic>=2.9.0
Requires-Dist: pymupdf>=1.25.1
Requires-Dist: pyspellchecker>=0.8.2
Requires-Dist: pytesseract>=0.3.13
Requires-Dist: rapidfuzz>=3.13.0
Requires-Dist: requests>=2.32.3
Requires-Dist: spacy==3.8.3
Requires-Dist: tenacity>=9.1.2
Requires-Dist: torch>=2.5.1
Requires-Dist: torchaudio>=2.5.1
Requires-Dist: torchvision>=0.20.1
Provides-Extra: dev
Requires-Dist: build>=1.3.0; extra == 'dev'
Requires-Dist: flake8>=7.1.1; extra == 'dev'
Requires-Dist: pytest-cov>=5.0.0; extra == 'dev'
Requires-Dist: pytest>=7.0.1; extra == 'dev'
Requires-Dist: twine>=6.2.0; extra == 'dev'
Requires-Dist: uv>=0.4.17; extra == 'dev'
Provides-Extra: django
Requires-Dist: django>=5.2; extra == 'django'
Provides-Extra: llm
Requires-Dist: hezar>=0.42.0; extra == 'llm'
Requires-Dist: ollama>=0.4.7; extra == 'llm'
Requires-Dist: tiktoken>=0.9.0; extra == 'llm'
Requires-Dist: transformers==4.44.2; extra == 'llm'
Provides-Extra: ocr
Requires-Dist: tesserocr>=2.8.0; extra == 'ocr'
Requires-Dist: verovio>=5.1.0; extra == 'ocr'
